keepassxc_browser/__init__.py
keepassxc_browser/connection_posix.py
keepassxc_browser/connection_win.py
keepassxc_browser/exceptions.py
keepassxc_browser/protocol.py
keepassxc_browser-0.1.6.dist-info/LICENSE
keepassxc_browser-0.1.6.dist-info/METADATA
keepassxc_browser-0.1.6.dist-info/WHEEL
keepassxc_browser-0.1.6.dist-info/top_level.txt
keepassxc_browser-0.1.6.dist-info/RECORD
