Metadata-Version: 2.1
Name: keepassxc-browser
Version: 0.1.6
Summary: Access the KeepassXC Browser API from python
Home-page: https://github.com/hrehfeld/python-keepassxc-browser
Author: Hauke Rehfeld
Author-email: pypi.org@haukerehfeld.de
License: AGPL-3.0
Platform: UNKNOWN
Classifier: Programming Language :: Python :: 3
Classifier: License :: OSI Approved :: GNU Affero General Public License v3 or later (AGPLv3+)
Classifier: Operating System :: OS Independent
Classifier: Topic :: Security
Classifier: Topic :: Software Development :: Libraries
Requires-Dist: pysodium
Requires-Dist: pywin32 ; platform_system == "Windows"
